ipmidb_tools-19.10.1.post2.data/scripts/ipmi-grabber
ipmidb_tools-19.10.1.post2.data/scripts/ipmiadm
ipmidb_tools-19.10.1.post2.dist-info/METADATA
ipmidb_tools-19.10.1.post2.dist-info/RECORD
ipmidb_tools-19.10.1.post2.dist-info/WHEEL
ipmidb_tools-19.10.1.post2.dist-info/top_level.txt
pyipmidb/__init__.py
pyipmidb/client.py
pyipmidb/helpers.py
pyipmidb/sanitizer.py
