Metadata-Version: 2.1
Name: ipmidb-tools
Version: 19.10.1.post2
Summary: Toolset for IPMI interactions at CERN Data Center
Home-page: https://gitlab.cern.ch/hw/ipmidb-tools
Author: Luca Gardi
Author-email: luca.gardi@cern.ch
License: GPL
Platform: UNKNOWN
